programming_game/__init__.py
programming_game/__main__.py
programming_game/client.py
programming_game/config.py
programming_game/connection_mixin.py
programming_game/db.py
programming_game/decorators.py
programming_game/logging.py
programming_game/message_processing.py
programming_game/protocol.py
programming_game/tick_loop.py
programming_game/extra/__init__.py
programming_game/extra/prometheus.py
programming_game/extra/zmq.py
programming_game/schema/__init__.py
programming_game/schema/events.py
programming_game/schema/game_object.py
programming_game/schema/intents.py
programming_game/schema/items.py
programming_game/schema/messages.py
programming_game/schema/other.py
programming_game/schema/position.py
programming_game/schema/quest.py
programming_game/schema/units.py
programming_game/structure/__init__.py
programming_game/structure/callable_script_wrapper.py
programming_game/structure/game_state.py
programming_game/structure/instance.py
programming_game/structure/instance_character.py
programming_game/structure/on_tick_response.py
programming_game/tasks/__init__.py
programming_game/tasks/task.py
programming_game/tasks/task_meta.py
programming_game/utils/__init__.py
programming_game/utils/helper.py
programming_game/utils/item_cache.py
programming_game-0.0.27.dist-info/.DS_Store
programming_game-0.0.27.dist-info/METADATA
programming_game-0.0.27.dist-info/WHEEL
programming_game-0.0.27.dist-info/top_level.txt
programming_game-0.0.27.dist-info/RECORD
