Metadata-Version: 2.4
Name: programming-game
Version: 0.0.27
Summary: A Python client for the Programming Game.
Author-email: Bastian Hoyer <dafire@gmail.com>
License: MIT
Project-URL: Homepage, https://github.com/bastianh/programming-game-python
Project-URL: Repository, https://github.com/bastianh/programming-game-python
Classifier: Development Status :: 1 - Planning
Classifier: Programming Language :: Python
Classifier: Programming Language :: Python :: 3.12
Classifier: License :: OSI Approved :: MIT License
Classifier: Operating System :: OS Independent
Requires-Python: >=3.11
Requires-Dist: msgspec>=0.19.0
Requires-Dist: rich>=14.1.0
Requires-Dist: watchdog>=6.0.0
Requires-Dist: websockets>=15.0.1
Requires-Dist: click>=8.1.7
Requires-Dist: python-dotenv>=1.1.1
Requires-Dist: pyyaml>=6.0.2
Requires-Dist: colorlog>=6.9.0
Requires-Dist: loguru>=0.7.3
Provides-Extra: db
Requires-Dist: sqlalchemy[asyncio]>=2.0.0; extra == "db"
Requires-Dist: psycopg2-binary>=2.9.0; extra == "db"
Requires-Dist: asyncpg>=0.30.0; extra == "db"
Provides-Extra: zmq
Requires-Dist: fastnanoid>=0.4.3; extra == "zmq"
Requires-Dist: pyzmq>=27.1.0; extra == "zmq"
Requires-Dist: tnetstring3>=0.3.1; extra == "zmq"
Provides-Extra: prometheus
Requires-Dist: aioprometheus[aiohttp]>=23.12.0; extra == "prometheus"
